PyScopedStorage/__init__.py
PyScopedStorage/android_objects.py
PyScopedStorage/filechooser.py
PyScopedStorage/io.py
PyScopedStorage/tools.py
PyScopedStorage/utils.py
pyscopedstorage-0.0.7.dist-info/LICENSE
pyscopedstorage-0.0.7.dist-info/METADATA
pyscopedstorage-0.0.7.dist-info/WHEEL
pyscopedstorage-0.0.7.dist-info/RECORD
